pySMARTS/__init__.py
pySMARTS/_version.py
pySMARTS/main.py
pySMARTS-0.0.1.dist-info/LICENSE.md
pySMARTS-0.0.1.dist-info/METADATA
pySMARTS-0.0.1.dist-info/WHEEL
pySMARTS-0.0.1.dist-info/top_level.txt
pySMARTS-0.0.1.dist-info/RECORD
